{"text": " This past week I made a guana tacos and it really shook the internet and I got a whole bunch of hate so let's talk about ethical eating. Now I totally get if you just won't eat a guana taco everybody has their limits that's fine. But overall that wasn't the main issue that people had in the comments so let's talk about it. Now when I made the original video I said that a guana's are an invasive species here in South Florida but just in case anyone's not sure of the criteria this is it specifically here in South Florida this is the impact that a guana's have on our local ecosystem. Due to the extreme cold temperatures we had this week that immobilized a lot of them in Florida fish and wildlife had drop off points and collected over 5,000 of them most of which ended up being euthanized. So rather than let the one that I found go to waste I decided to make tacos and I would argue that it's the most ethical taco you could possibly have. Locally hunting and sourcing your own food in general saves the entire planet from greenhouse gases of your food having to travel around the world to get to your plate. When it comes to invasive species then you're not only helping the entire planet by not flying it across the world but you're also helping your local ecosystem. That brings us to point number two. You all do realize that chicken and beef and all of that comes from somewhere right? It comes from farms and personally after seeing the conditions that many of these animals are in at these farms I think that these have it way better off. They have a great life and then one bad day rather than some of the animals on these farms having an awful life. And that brings us to point number three. Why don't you just go vegan? And personally I don't have any beef with vegans but I also will say that I do think that this is also better than even going vegan and here's why. A lot of our produce, fruits and vegetables as well as vegan products come from monocultured crops and those have to grow somewhere which means that areas for wildlife habitat have to be bulldozed in order to do so. And then on top of that they have to fly over to get to your table. Hopefully this explains the why behind my iguana tacos and challenges people to think about where their food comes from. Until next time get outside and see what you can find.", "segments": [{"id": 0, "seek": 0, "start": 0.0, "end": 3.7600000000000002, "text": " This past week I made a guana tacos and it really shook the internet and I got a whole", "tokens": [50364, 639, 1791, 1243, 286, 1027, 257, 695, 2095, 34776, 293, 309, 534, 28438, 264, 4705, 293, 286, 658, 257, 1379, 50552], "temperature": 0.0, "avg_logprob": -0.16800782820757698, "compression_ratio": 1.8162162162162163, "no_speech_prob": 0.01741115003824234}, {"id": 1, "seek": 0, "start": 3.7600000000000002, "end": 6.0, "text": " bunch of hate so let's talk about ethical eating.", "tokens": [50552, 3840, 295, 4700, 370, 718, 311, 751, 466, 18890, 3936, 13, 50664], "temperature": 0.0, "avg_logprob": -0.16800782820757698, "compression_ratio": 1.8162162162162163, "no_speech_prob": 0.01741115003824234}, {"id": 2, "seek": 0, "start": 6.0, "end": 9.96, "text": " Now I totally get if you just won't eat a guana taco everybody has their limits that's", "tokens": [50664, 823, 286, 3879, 483, 498, 291, 445, 1582, 380, 1862, 257, 695, 2095, 34101, 2201, 575, 641, 10406, 300, 311, 50862], "temperature": 0.0, "avg_logprob": -0.16800782820757698, "compression_ratio": 1.8162162162162163, "no_speech_prob": 0.01741115003824234}, {"id": 3, "seek": 0, "start": 9.96, "end": 10.96, "text": " fine.", "tokens": [50862, 2489, 13, 50912], "temperature": 0.0, "avg_logprob": -0.16800782820757698, "compression_ratio": 1.8162162162162163, "no_speech_prob": 0.01741115003824234}, {"id": 4, "seek": 0, "start": 10.96, "end": 13.64, "text": " But overall that wasn't the main issue that people had in the comments so let's talk", "tokens": [50912, 583, 4787, 300, 2067, 380, 264, 2135, 2734, 300, 561, 632, 294, 264, 3053, 370, 718, 311, 751, 51046], "temperature": 0.0, "avg_logprob": -0.16800782820757698, "compression_ratio": 1.8162162162162163, "no_speech_prob": 0.01741115003824234}, {"id": 5, "seek": 0, "start": 13.64, "end": 14.64, "text": " about it.", "tokens": [51046, 466, 309, 13, 51096], "temperature": 0.0, "avg_logprob": -0.16800782820757698, "compression_ratio": 1.8162162162162163, "no_speech_prob": 0.01741115003824234}, {"id": 6, "seek": 0, "start": 14.64, "end": 17.400000000000002, "text": " Now when I made the original video I said that a guana's are an invasive species here", "tokens": [51096, 823, 562, 286, 1027, 264, 3380, 960, 286, 848, 300, 257, 695, 2095, 311, 366, 364, 30894, 6172, 510, 51234], "temperature": 0.0, "avg_logprob": -0.16800782820757698, "compression_ratio": 1.8162162162162163, "no_speech_prob": 0.01741115003824234}, {"id": 7, "seek": 0, "start": 17.400000000000002, "end": 22.0, "text": " in South Florida but just in case anyone's not sure of the criteria this is it specifically", "tokens": [51234, 294, 4242, 9117, 457, 445, 294, 1389, 2878, 311, 406, 988, 295, 264, 11101, 341, 307, 309, 4682, 51464], "temperature": 0.0, "avg_logprob": -0.16800782820757698, "compression_ratio": 1.8162162162162163, "no_speech_prob": 0.01741115003824234}, {"id": 8, "seek": 0, "start": 22.0, "end": 26.080000000000002, "text": " here in South Florida this is the impact that a guana's have on our local ecosystem.", "tokens": [51464, 510, 294, 4242, 9117, 341, 307, 264, 2712, 300, 257, 695, 2095, 311, 362, 322, 527, 2654, 11311, 13, 51668], "temperature": 0.0, "avg_logprob": -0.16800782820757698, "compression_ratio": 1.8162162162162163, "no_speech_prob": 0.01741115003824234}, {"id": 9, "seek": 0, "start": 26.080000000000002, "end": 29.2, "text": " Due to the extreme cold temperatures we had this week that immobilized a lot of them", "tokens": [51668, 18980, 281, 264, 8084, 3554, 12633, 321, 632, 341, 1243, 300, 3397, 21725, 1602, 257, 688, 295, 552, 51824], "temperature": 0.0, "avg_logprob": -0.16800782820757698, "compression_ratio": 1.8162162162162163, "no_speech_prob": 0.01741115003824234}, {"id": 10, "seek": 2920, "start": 29.2, "end": 33.32, "text": " in Florida fish and wildlife had drop off points and collected over 5,000 of them most", "tokens": [50364, 294, 9117, 3506, 293, 19199, 632, 3270, 766, 2793, 293, 11087, 670, 1025, 11, 1360, 295, 552, 881, 50570], "temperature": 0.0, "avg_logprob": -0.12888978197683695, "compression_ratio": 1.7411444141689374, "no_speech_prob": 0.005947575904428959}, {"id": 11, "seek": 2920, "start": 33.32, "end": 34.76, "text": " of which ended up being euthanized.", "tokens": [50570, 295, 597, 4590, 493, 885, 308, 2910, 282, 1602, 13, 50642], "temperature": 0.0, "avg_logprob": -0.12888978197683695, "compression_ratio": 1.7411444141689374, "no_speech_prob": 0.005947575904428959}, {"id": 12, "seek": 2920, "start": 34.76, "end": 38.12, "text": " So rather than let the one that I found go to waste I decided to make tacos and I would", "tokens": [50642, 407, 2831, 813, 718, 264, 472, 300, 286, 1352, 352, 281, 5964, 286, 3047, 281, 652, 34776, 293, 286, 576, 50810], "temperature": 0.0, "avg_logprob": -0.12888978197683695, "compression_ratio": 1.7411444141689374, "no_speech_prob": 0.005947575904428959}, {"id": 13, "seek": 2920, "start": 38.12, "end": 41.12, "text": " argue that it's the most ethical taco you could possibly have.", "tokens": [50810, 9695, 300, 309, 311, 264, 881, 18890, 34101, 291, 727, 6264, 362, 13, 50960], "temperature": 0.0, "avg_logprob": -0.12888978197683695, "compression_ratio": 1.7411444141689374, "no_speech_prob": 0.005947575904428959}, {"id": 14, "seek": 2920, "start": 41.12, "end": 44.56, "text": " Locally hunting and sourcing your own food in general saves the entire planet from greenhouse", "tokens": [50960, 12859, 379, 12599, 293, 11006, 2175, 428, 1065, 1755, 294, 2674, 19155, 264, 2302, 5054, 490, 22126, 51132], "temperature": 0.0, "avg_logprob": -0.12888978197683695, "compression_ratio": 1.7411444141689374, "no_speech_prob": 0.005947575904428959}, {"id": 15, "seek": 2920, "start": 44.56, "end": 48.239999999999995, "text": " gases of your food having to travel around the world to get to your plate.", "tokens": [51132, 21452, 295, 428, 1755, 1419, 281, 3147, 926, 264, 1002, 281, 483, 281, 428, 5924, 13, 51316], "temperature": 0.0, "avg_logprob": -0.12888978197683695, "compression_ratio": 1.7411444141689374, "no_speech_prob": 0.005947575904428959}, {"id": 16, "seek": 2920, "start": 48.239999999999995, "end": 51.8, "text": " When it comes to invasive species then you're not only helping the entire planet by not flying", "tokens": [51316, 1133, 309, 1487, 281, 30894, 6172, 550, 291, 434, 406, 787, 4315, 264, 2302, 5054, 538, 406, 7137, 51494], "temperature": 0.0, "avg_logprob": -0.12888978197683695, "compression_ratio": 1.7411444141689374, "no_speech_prob": 0.005947575904428959}, {"id": 17, "seek": 2920, "start": 51.8, "end": 54.92, "text": " it across the world but you're also helping your local ecosystem.", "tokens": [51494, 309, 2108, 264, 1002, 457, 291, 434, 611, 4315, 428, 2654, 11311, 13, 51650], "temperature": 0.0, "avg_logprob": -0.12888978197683695, "compression_ratio": 1.7411444141689374, "no_speech_prob": 0.005947575904428959}, {"id": 18, "seek": 2920, "start": 54.92, "end": 56.4, "text": " That brings us to point number two.", "tokens": [51650, 663, 5607, 505, 281, 935, 1230, 732, 13, 51724], "temperature": 0.0, "avg_logprob": -0.12888978197683695, "compression_ratio": 1.7411444141689374, "no_speech_prob": 0.005947575904428959}, {"id": 19, "seek": 5640, "start": 56.4, "end": 60.36, "text": " You all do realize that chicken and beef and all of that comes from somewhere right?", "tokens": [50364, 509, 439, 360, 4325, 300, 4662, 293, 9256, 293, 439, 295, 300, 1487, 490, 4079, 558, 30, 50562], "temperature": 0.0, "avg_logprob": -0.12070306589905645, "compression_ratio": 1.8599348534201954, "no_speech_prob": 0.09733252972364426}, {"id": 20, "seek": 5640, "start": 60.36, "end": 64.08, "text": " It comes from farms and personally after seeing the conditions that many of these animals", "tokens": [50562, 467, 1487, 490, 20366, 293, 5665, 934, 2577, 264, 4487, 300, 867, 295, 613, 4882, 50748], "temperature": 0.0, "avg_logprob": -0.12070306589905645, "compression_ratio": 1.8599348534201954, "no_speech_prob": 0.09733252972364426}, {"id": 21, "seek": 5640, "start": 64.08, "end": 66.96, "text": " are in at these farms I think that these have it way better off.", "tokens": [50748, 366, 294, 412, 613, 20366, 286, 519, 300, 613, 362, 309, 636, 1101, 766, 13, 50892], "temperature": 0.0, "avg_logprob": -0.12070306589905645, "compression_ratio": 1.8599348534201954, "no_speech_prob": 0.09733252972364426}, {"id": 22, "seek": 5640, "start": 66.96, "end": 70.24, "text": " They have a great life and then one bad day rather than some of the animals on these", "tokens": [50892, 814, 362, 257, 869, 993, 293, 550, 472, 1578, 786, 2831, 813, 512, 295, 264, 4882, 322, 613, 51056], "temperature": 0.0, "avg_logprob": -0.12070306589905645, "compression_ratio": 1.8599348534201954, "no_speech_prob": 0.09733252972364426}, {"id": 23, "seek": 5640, "start": 70.24, "end": 72.08, "text": " farms having an awful life.", "tokens": [51056, 20366, 1419, 364, 11232, 993, 13, 51148], "temperature": 0.0, "avg_logprob": -0.12070306589905645, "compression_ratio": 1.8599348534201954, "no_speech_prob": 0.09733252972364426}, {"id": 24, "seek": 5640, "start": 72.08, "end": 73.84, "text": " And that brings us to point number three.", "tokens": [51148, 400, 300, 5607, 505, 281, 935, 1230, 1045, 13, 51236], "temperature": 0.0, "avg_logprob": -0.12070306589905645, "compression_ratio": 1.8599348534201954, "no_speech_prob": 0.09733252972364426}, {"id": 25, "seek": 5640, "start": 73.84, "end": 75.44, "text": " Why don't you just go vegan?", "tokens": [51236, 1545, 500, 380, 291, 445, 352, 12824, 30, 51316], "temperature": 0.0, "avg_logprob": -0.12070306589905645, "compression_ratio": 1.8599348534201954, "no_speech_prob": 0.09733252972364426}, {"id": 26, "seek": 5640, "start": 75.44, "end": 79.03999999999999, "text": " And personally I don't have any beef with vegans but I also will say that I do think that", "tokens": [51316, 400, 5665, 286, 500, 380, 362, 604, 9256, 365, 24366, 599, 457, 286, 611, 486, 584, 300, 286, 360, 519, 300, 51496], "temperature": 0.0, "avg_logprob": -0.12070306589905645, "compression_ratio": 1.8599348534201954, "no_speech_prob": 0.09733252972364426}, {"id": 27, "seek": 5640, "start": 79.03999999999999, "end": 82.2, "text": " this is also better than even going vegan and here's why.", "tokens": [51496, 341, 307, 611, 1101, 813, 754, 516, 12824, 293, 510, 311, 983, 13, 51654], "temperature": 0.0, "avg_logprob": -0.12070306589905645, "compression_ratio": 1.8599348534201954, "no_speech_prob": 0.09733252972364426}, {"id": 28, "seek": 8220, "start": 82.2, "end": 86.24000000000001, "text": " A lot of our produce, fruits and vegetables as well as vegan products come from monocultured", "tokens": [50364, 316, 688, 295, 527, 5258, 11, 12148, 293, 9320, 382, 731, 382, 12824, 3383, 808, 490, 1108, 905, 723, 3831, 50566], "temperature": 0.0, "avg_logprob": -0.15284051213945662, "compression_ratio": 1.6690909090909092, "no_speech_prob": 0.011600460857152939}, {"id": 29, "seek": 8220, "start": 86.24000000000001, "end": 90.24000000000001, "text": " crops and those have to grow somewhere which means that areas for wildlife habitat have", "tokens": [50566, 16829, 293, 729, 362, 281, 1852, 4079, 597, 1355, 300, 3179, 337, 19199, 20110, 362, 50766], "temperature": 0.0, "avg_logprob": -0.15284051213945662, "compression_ratio": 1.6690909090909092, "no_speech_prob": 0.011600460857152939}, {"id": 30, "seek": 8220, "start": 90.24000000000001, "end": 92.2, "text": " to be bulldozed in order to do so.", "tokens": [50766, 281, 312, 4693, 2595, 11312, 294, 1668, 281, 360, 370, 13, 50864], "temperature": 0.0, "avg_logprob": -0.15284051213945662, "compression_ratio": 1.6690909090909092, "no_speech_prob": 0.011600460857152939}, {"id": 31, "seek": 8220, "start": 92.2, "end": 94.96000000000001, "text": " And then on top of that they have to fly over to get to your table.", "tokens": [50864, 400, 550, 322, 1192, 295, 300, 436, 362, 281, 3603, 670, 281, 483, 281, 428, 3199, 13, 51002], "temperature": 0.0, "avg_logprob": -0.15284051213945662, "compression_ratio": 1.6690909090909092, "no_speech_prob": 0.011600460857152939}, {"id": 32, "seek": 8220, "start": 94.96000000000001, "end": 98.52000000000001, "text": " Hopefully this explains the why behind my iguana tacos and challenges people to think", "tokens": [51002, 10429, 341, 13948, 264, 983, 2261, 452, 8508, 20070, 34776, 293, 4759, 561, 281, 519, 51180], "temperature": 0.0, "avg_logprob": -0.15284051213945662, "compression_ratio": 1.6690909090909092, "no_speech_prob": 0.011600460857152939}, {"id": 33, "seek": 8220, "start": 98.52000000000001, "end": 99.84, "text": " about where their food comes from.", "tokens": [51180, 466, 689, 641, 1755, 1487, 490, 13, 51246], "temperature": 0.0, "avg_logprob": -0.15284051213945662, "compression_ratio": 1.6690909090909092, "no_speech_prob": 0.011600460857152939}, {"id": 34, "seek": 8220, "start": 99.84, "end": 101.76, "text": " Until next time get outside and see what you can find.", "tokens": [51246, 9088, 958, 565, 483, 2380, 293, 536, 437, 291, 393, 915, 13, 51342], "temperature": 0.0, "avg_logprob": -0.15284051213945662, "compression_ratio": 1.6690909090909092, "no_speech_prob": 0.011600460857152939}], "language": "en"}