{"text": " You're so freaking cute I think I could get used to you Oh oh Got me like Oh oh Oh oh Oh oh Oh oh And when did you come from baby Please don't tell me you're afraid No", "segments": [{"id": 0, "seek": 0, "start": 0.0, "end": 2.0, "text": " You're so freaking cute", "tokens": [50364, 509, 434, 370, 14612, 4052, 50464], "temperature": 0.2, "avg_logprob": -0.3772911365215595, "compression_ratio": 1.3577235772357723, "no_speech_prob": 0.5524188280105591}, {"id": 1, "seek": 0, "start": 2.0, "end": 4.0, "text": " I think I could get used to you", "tokens": [50464, 286, 519, 286, 727, 483, 1143, 281, 291, 50564], "temperature": 0.2, "avg_logprob": -0.3772911365215595, "compression_ratio": 1.3577235772357723, "no_speech_prob": 0.5524188280105591}, {"id": 2, "seek": 0, "start": 4.0, "end": 5.0, "text": " Oh oh", "tokens": [50564, 876, 1954, 50614], "temperature": 0.2, "avg_logprob": -0.3772911365215595, "compression_ratio": 1.3577235772357723, "no_speech_prob": 0.5524188280105591}, {"id": 3, "seek": 0, "start": 5.0, "end": 6.0, "text": " Got me like", "tokens": [50614, 5803, 385, 411, 50664], "temperature": 0.2, "avg_logprob": -0.3772911365215595, "compression_ratio": 1.3577235772357723, "no_speech_prob": 0.5524188280105591}, {"id": 4, "seek": 0, "start": 6.0, "end": 7.0, "text": " Oh oh", "tokens": [50664, 876, 1954, 50714], "temperature": 0.2, "avg_logprob": -0.3772911365215595, "compression_ratio": 1.3577235772357723, "no_speech_prob": 0.5524188280105591}, {"id": 5, "seek": 0, "start": 7.0, "end": 8.0, "text": " Oh oh", "tokens": [50714, 876, 1954, 50764], "temperature": 0.2, "avg_logprob": -0.3772911365215595, "compression_ratio": 1.3577235772357723, "no_speech_prob": 0.5524188280105591}, {"id": 6, "seek": 0, "start": 8.0, "end": 9.0, "text": " Oh oh", "tokens": [50764, 876, 1954, 50814], "temperature": 0.2, "avg_logprob": -0.3772911365215595, "compression_ratio": 1.3577235772357723, "no_speech_prob": 0.5524188280105591}, {"id": 7, "seek": 0, "start": 9.0, "end": 10.0, "text": " Oh oh", "tokens": [50814, 876, 1954, 50864], "temperature": 0.2, "avg_logprob": -0.3772911365215595, "compression_ratio": 1.3577235772357723, "no_speech_prob": 0.5524188280105591}, {"id": 8, "seek": 0, "start": 10.0, "end": 12.0, "text": " And when did you come from baby", "tokens": [50864, 400, 562, 630, 291, 808, 490, 3186, 50964], "temperature": 0.2, "avg_logprob": -0.3772911365215595, "compression_ratio": 1.3577235772357723, "no_speech_prob": 0.5524188280105591}, {"id": 9, "seek": 0, "start": 12.0, "end": 14.0, "text": " Please don't tell me you're afraid", "tokens": [50964, 2555, 500, 380, 980, 385, 291, 434, 4638, 51064], "temperature": 0.2, "avg_logprob": -0.3772911365215595, "compression_ratio": 1.3577235772357723, "no_speech_prob": 0.5524188280105591}, {"id": 10, "seek": 0, "start": 14.0, "end": 15.0, "text": " No", "tokens": [51064, 883, 51114], "temperature": 0.2, "avg_logprob": -0.3772911365215595, "compression_ratio": 1.3577235772357723, "no_speech_prob": 0.5524188280105591}], "language": "en"}